{
    "name": "icebearjs",
    "title": "IcebearJS",
    "description": "jQuery plugin which provides a development elements",
    "keywords": [
        "icebear",
        "ui",
        "development"
    ],
    "version": "1.0.1",
    "author": {
        "name": "Miguel Gonzalez",
        "url": "http://my-reality.de/about"
    },
    "maintainers": [
        {
            "name": "Miguel Gonzalez",
            "email": "miguel-gonzalez@gmx.de",
            "url": "http://my-reality.de"
        }
    ],
    "licenses": [
        {
            "type": "GPL2",
            "url": "https://github.com/MyRealityCoding/icebearjs/LICENCE"
        }
    ],
    "bugs": "https://github.com/MyRealityCoding/icebearjs/issues",
    "homepage": "http://icebearjs.my-reality.de",
    "docs": "https://github.com/MyRealityCoding/icebearjs#getting-started",
    "download": "https://github.com/MyRealityCoding/icebearjs/releases",
    "dependencies": {
        "jquery": ">=1.5"
    }
}
